README.rst
setup.py
ip2locale/__init__.py
ip2locale/metadata.py
ip2locale/scripts.py
ip2locale.egg-info/PKG-INFO
ip2locale.egg-info/SOURCES.txt
ip2locale.egg-info/dependency_links.txt
ip2locale.egg-info/requires.txt
ip2locale.egg-info/top_level.txt
ip2locale/Provider/__init__.py
ip2locale/Provider/taobao.py
ip2locale/utils/__init__.py
scripts/ip2locale