Metadata-Version: 1.0
Name: ip2locale
Version: 0.1.0
Summary: ipv4 to locale
Home-page: https://github.com/pengyao/ip2locale
Author: pengyao
Author-email: pengyao@pengyao.org
License: Apache License V2.0
Platform: UNKNOWN
